{
  "10": {
    "sunrise": "7:06:22 AM",
    "sunset": "6:42:04 PM"
  },
  "11": {
    "sunrise": "7:04:35 AM",
    "sunset": "6:43:19 PM"
  },
  "12": {
    "sunrise": "7:02:48 AM",
    "sunset": "6:44:33 PM"
  },
  "13": {
    "sunrise": "7:01:00 AM",
    "sunset": "6:45:47 PM"
  },
  "14": {
    "sunrise": "6:59:12 AM",
    "sunset": "6:47:01 PM"
  },
  "15": {
    "sunrise": "6:57:24 AM",
    "sunset": "6:48:15 PM"
  },
  "16": {
    "sunrise": "6:55:35 AM",
    "sunset": "6:49:29 PM"
  },
  "17": {
    "sunrise": "6:53:46 AM",
    "sunset": "6:50:42 PM"
  },
  "18": {
    "sunrise": "6:51:57 AM",
    "sunset": "6:51:55 PM"
  },
  "19": {
    "sunrise": "6:50:07 AM",
    "sunset": "6:53:08 PM"
  },
  "20": {
    "sunrise": "6:48:18 AM",
    "sunset": "6:54:21 PM"
  },
  "21": {
    "sunrise": "6:46:28 AM",
    "sunset": "6:55:33 PM"
  },
  "22": {
    "sunrise": "6:44:38 AM",
    "sunset": "6:56:46 PM"
  },
  "23": {
    "sunrise": "6:42:48 AM",
    "sunset": "6:57:58 PM"
  },
  "24": {
    "sunrise": "6:40:58 AM",
    "sunset": "6:59:10 PM"
  },
  "25": {
    "sunrise": "6:39:08 AM",
    "sunset": "7:00:22 PM"
  },
  "26": {
    "sunrise": "6:37:18 AM",
    "sunset": "7:01:34 PM"
  },
  "27": {
    "sunrise": "6:35:28 AM",
    "sunset": "7:02:46 PM"
  },
  "28": {
    "sunrise": "6:33:39 AM",
    "sunset": "7:03:58 PM"
  },
  "29": {
    "sunrise": "6:31:49 AM",
    "sunset": "7:05:10 PM"
  },
  "30": {
    "sunrise": "6:30:00 AM",
    "sunset": "7:06:21 PM"
  },
  "31": {
    "sunrise": "6:28:11 AM",
    "sunset": "7:07:33 PM"
  },
  "01": {
    "sunrise": "7:21:58 AM",
    "sunset": "6:30:37 PM"
  },
  "02": {
    "sunrise": "7:20:17 AM",
    "sunset": "6:31:55 PM"
  },
  "03": {
    "sunrise": "7:18:35 AM",
    "sunset": "6:33:12 PM"
  },
  "04": {
    "sunrise": "7:16:52 AM",
    "sunset": "6:34:29 PM"
  },
  "05": {
    "sunrise": "7:15:08 AM",
    "sunset": "6:35:46 PM"
  },
  "06": {
    "sunrise": "7:13:24 AM",
    "sunset": "6:37:02 PM"
  },
  "07": {
    "sunrise": "7:11:40 AM",
    "sunset": "6:38:18 PM"
  },
  "08": {
    "sunrise": "7:09:54 AM",
    "sunset": "6:39:33 PM"
  },
  "09": {
    "sunrise": "7:08:09 AM",
    "sunset": "6:40:49 PM"
  }
}